{
  "timestamp": "2026-03-19T21:32:38.491931",
  "analyzed_blocks": 13,
  "patterns_discovered": 3,
  "clusters": [
    {
      "cluster_id": "pattern_a97b97",
      "member_count": 4,
      "members": [
        "pulse_78a466af",
        "pulse_d6d6181d",
        "pulse_eae60f67",
        "pulse_27b35440"
      ]
    },
    {
      "cluster_id": "pattern_6a7c0f",
      "member_count": 6,
      "members": [
        "ref_30e6c8f8",
        "ref_3dfe543d",
        "ref_53ba76f4",
        "ref_8c452de6",
        "ref_a013331b",
        "ref_d9fac688"
      ]
    },
    {
      "cluster_id": "pattern_65d012",
      "member_count": 3,
      "members": [
        "ref_46eddfe1",
        "ref_963b52b3",
        "ref_e721253c"
      ]
    }
  ]
}